easySecurity/__init__.py
easySecurity-0.0.1.dist-info/LICENSE
easySecurity-0.0.1.dist-info/METADATA
easySecurity-0.0.1.dist-info/WHEEL
easySecurity-0.0.1.dist-info/top_level.txt
easySecurity-0.0.1.dist-info/RECORD
