Metadata-Version: 2.1
Name: easySecurity
Version: 0.0.1
Summary: easySecurity is a simple encryption of files and strings.
Home-page: https://github.com/Password-Classified/easyML
Author: Password-Classified
Author-email: user@example.com
License: UNKNOWN
Project-URL: Bug Tracker, https://github.com/Password-Classified/easyML/issues
Keywords: python,security,encryption,hashing,easySecurity,eastSecurity
Platform: UNKNOWN
Classifier: Development Status :: 1 - Planning
Classifier: Intended Audience :: Developers
Classifier: Programming Language :: Python :: 3
Classifier: Operating System :: Unix
Classifier: Operating System :: MacOS :: MacOS X
Classifier: Operating System :: Microsoft :: Windows
Requires-Python: >=3.6
